dart_board/__init__.py
dart_board/constants.py
dart_board/darts.py
dart_board/forward_pop_synth.py
dart_board/plot_system_evolution.py
dart_board/plotting.py
dart_board/posterior.py
dart_board/priors.py
dart_board/utils.py
dart_board/cosmo/__init__.py
dart_board/cosmo/metallicity.py
dart_board/cosmo/sfr.py
dart_board/cosmo/utilities.py
dart_board/sf_history/__init__.py
dart_board/sf_history/flat.py
dart_board/sf_history/lmc.py
dart_board/sf_history/load_lmc_data.py
dart_board/sf_history/load_smc_data.py
dart_board/sf_history/sf_plotting.py
dart_board-1.1.0.dist-info/LICENSE
dart_board-1.1.0.dist-info/METADATA
dart_board-1.1.0.dist-info/WHEEL
dart_board-1.1.0.dist-info/top_level.txt
dart_board-1.1.0.dist-info/RECORD
