Metadata-Version: 2.1
Name: dart-board
Version: 1.1.0
Summary: Binary Population Synthesis with MCMC
Home-page: http://github.com/astroJeff/dart_board
Author: Jeff J. Andrews
Author-email: andrews@physics.uoc.gr
License: MIT
Platform: UNKNOWN
